{
  "lastUpdated": "2022-07-17T21:28:24.110Z",
  "articles": [
    {
      "publication": "CNN",
      "handle": "CNN",
      "url": "https://www.cnn.com/interactive/2022/07/us/uvalde-report-full-document/",
      "headline": "Read the full Uvalde report",
      "timestamp": null
    },
    {
      "publication": "CNN",
      "handle": "CNN",
      "url": "https://www.cnn.com/interactive/2022/07/us/cnn-5-things-news-quiz-july-14-sec/",
      "headline": "The average score for this week's news quiz is 7.2. Think you can do better?",
      "timestamp": null
    },
    {
      "publication": "CNN",
      "handle": "CNN",
      "url": "https://www.cnn.com/travel/article/interactive-inflight-entertainment-cameras/index.html",
      "headline": "Cameras, microphones and algorithms: How inflight entertainment is getting personal",
      "timestamp": "2022-07-15T10:21:44.000Z"
    },
    {
      "publication": "CNN",
      "handle": "CNN",
      "url": "https://www.cnn.com/interactive/2022/07/search-for-life/",
      "headline": "Are we alone?",
      "timestamp": null
    },
    {
      "publication": "CNN",
      "handle": "CNN",
      "url": "https://www.cnn.com/interactive/2022/07/us/cnn-5-things-news-quiz-july-7-sec/",
      "headline": "The average score for this week's news quiz is 7.6. Think you can do better?",
      "timestamp": null
    }
  ]
}